AUTHORS
LICENSE
MANIFEST.in
README.rst
setup.py
docker_startup/__init__.py
docker_startup/tests.py
docker_startup.egg-info/PKG-INFO
docker_startup.egg-info/SOURCES.txt
docker_startup.egg-info/dependency_links.txt
docker_startup.egg-info/not-zip-safe
docker_startup.egg-info/top_level.txt
docker_startup/base/__init__.py
docker_startup/django/__init__.py
docker_startup/java/__init__.py
docker_startup/php/__init__.py
docs/Makefile
docs/conf.py
docs/index.txt
docs/make.bat
docs/_ext/djangodocs.py
docs/_static/logo.png
docs/_templates/sidebarintro.html
docs/_templates/sidebarlogo.html
docs/_themes/.gitignore
docs/_themes/LICENSE
docs/_themes/README.rst
docs/_themes/flask_theme_support.py
docs/_themes/kr/layout.html
docs/_themes/kr/relations.html
docs/_themes/kr/theme.conf
docs/_themes/kr/static/flasky.css_t
docs/_themes/kr_small/layout.html
docs/_themes/kr_small/theme.conf
docs/_themes/kr_small/static/flasky.css_t
docs/dev/authors.txt
docs/dev/changelog.txt
docs/dev/contribute.txt
docs/dev/todo.txt
docs/user/install.txt
docs/user/intro.txt
docs/user/quickstart.txt