Metadata-Version: 1.1
Name: docker-startup
Version: 0.6
Summary: Startup/Install scripts for docker-based VMs.
Home-page: https://bitbucket.org/dpaw/docker-startup
Author: Tomas Krajca, Scott Percival
Author-email: Tomas.Krajca@dpaw.wa.gov.au, Scott.Percival@dpaw.wa.gov.au
License: BSD License
Keywords: docker dockerfile startup script dpaw
Platform: UNKNOWN
Classifier: Development Status :: 4 - Beta
Classifier: License :: OSI Approved :: BSD License
Classifier: Intended Audience :: Developers
Classifier: Programming Language :: Python
Classifier: Programming Language :: Python :: 2
Classifier: Programming Language :: Python :: 3
